LICENSE.txt
MANIFEST.in
README.md
requirements-dev.txt
requirements.txt
setup.py
Filepool.egg-info/PKG-INFO
Filepool.egg-info/SOURCES.txt
Filepool.egg-info/dependency_links.txt
Filepool.egg-info/requires.txt
Filepool.egg-info/top_level.txt
src/Filepool/FPBufferInputStream.py
src/Filepool/FPBufferOutputStream.py
src/Filepool/FPClientException.py
src/Filepool/FPClip.py
src/Filepool/FPException.py
src/Filepool/FPFileInputStream.py
src/Filepool/FPFileOutputStream.py
src/Filepool/FPLibrary.py
src/Filepool/FPMonitor.py
src/Filepool/FPNetException.py
src/Filepool/FPPool.py
src/Filepool/FPQuery.py
src/Filepool/FPQueryExpression.py
src/Filepool/FPQueryResult.py
src/Filepool/FPRetention.py
src/Filepool/FPServerException.py
src/Filepool/FPStream.py
src/Filepool/FPTag.py
src/Filepool/FPTime.py
src/Filepool/__init__.py
src/Filepool/connector.py
src/Filepool/util.py
src/Filepool.egg-info/PKG-INFO
src/Filepool.egg-info/SOURCES.txt
src/Filepool.egg-info/dependency_links.txt
src/Filepool.egg-info/requires.txt
src/Filepool.egg-info/top_level.txt
src/native/pycentera.c
test/test_FPPool.py
test/test_clusterinfo.py
test/test_connector.py
test/test_connector_read.py
test/test_query.py
test/test_read.py
test/test_store.py