Metadata-Version: 1.1
Name: Filepool
Version: 1.3rc3
Summary: EMC Centera Content Addressable Storage binding library.
Home-page: https://github.com/ioggstream/caspython-centera
Author: Roberto Polli
Author-email: roberto.polli@par-tec.it
License: #########################################################################
